wxflows_client/__init__.py
wxflows_client/flow.py
wxflows_client/rag.py
wxflows_client/utils/build_query.py
wxflows_client/utils/constants.py
wxflows_client/utils/graphql_helpers.py
wxflows_client/utils/utils.py
wxflows_client-0.1.0.dist-info/LICENSE
wxflows_client-0.1.0.dist-info/METADATA
wxflows_client-0.1.0.dist-info/WHEEL
wxflows_client-0.1.0.dist-info/top_level.txt
wxflows_client-0.1.0.dist-info/RECORD
